torch_yolo3/__init__.py
torch_yolo3/augment.py
torch_yolo3/datasets.py
torch_yolo3/evaluate.py
torch_yolo3/logger.py
torch_yolo3/models.py
torch_yolo3/utils.py
torch_yolo3/visual.py
torch_yolo3-0.1.1.dist-info/LICENSE
torch_yolo3-0.1.1.dist-info/METADATA
torch_yolo3-0.1.1.dist-info/WHEEL
torch_yolo3-0.1.1.dist-info/top_level.txt
torch_yolo3-0.1.1.dist-info/RECORD
