Metadata-Version: 2.1
Name: torch-yolo3
Version: 0.1.1
Summary: YOLO v3 in PyTorch
Home-page: https://github.com/Borda/PyTorch-YOLOv3
Author: Erik Linder-Noren
Author-email: eriklindernoren@gmail.com
License: UNKNOWN
Keywords: Yolo CNN object-detector pytorch
Platform: UNKNOWN
Classifier: Development Status :: 3 - Alpha
Classifier: Intended Audience :: Developers
Classifier: License :: OSI Approved :: MIT License
Classifier: Programming Language :: Python :: 3
Classifier: Programming Language :: Python :: 3.6
Classifier: Programming Language :: Python :: 3.7
Classifier: Programming Language :: Python :: 3.8
Requires-Dist: numpy
Requires-Dist: torch (>=1.6)
Requires-Dist: torchvision
Requires-Dist: matplotlib
Requires-Dist: tensorboard
Requires-Dist: terminaltables
Requires-Dist: tqdm
Requires-Dist: pathos
Requires-Dist: PyYAML
Requires-Dist: torch-optimizer
